kompa/__init__.py
kompa/__main__.py
kompa/kompa.py
kompa-0.1.0.dist-info/licenses/LICENSE
kompa-0.1.0.dist-info/METADATA
kompa-0.1.0.dist-info/WHEEL
kompa-0.1.0.dist-info/entry_points.txt
kompa-0.1.0.dist-info/top_level.txt
kompa-0.1.0.dist-info/RECORD
