Metadata-Version: 2.4
Name: kompa
Version: 0.1.0
Summary: Compression-based k-nearest neighbors classifier for biological sequence classification
Author: Dániel Májer
License-Expression: MIT
Project-URL: Homepage, https://github.com/heloint/kompa
Project-URL: Repository, https://github.com/heloint/kompa
Project-URL: Issues, https://github.com/heloint/kompa/issues
Keywords: bioinformatics,sequence-classification,compression,knn,ncd
Classifier: Development Status :: 3 - Alpha
Classifier: Intended Audience :: Science/Research
Classifier: Programming Language :: Python :: 3
Classifier: Programming Language :: Python :: 3.9
Classifier: Programming Language :: Python :: 3.10
Classifier: Programming Language :: Python :: 3.11
Classifier: Programming Language :: Python :: 3.12
Classifier: Topic :: Scientific/Engineering :: Bio-Informatics
Requires-Python: >=3.9
License-File: LICENSE
Requires-Dist: lz4>=4.0.0
Provides-Extra: test
Requires-Dist: pytest>=7.0.0; extra == "test"
Requires-Dist: pytest-cov>=4.0.0; extra == "test"
Dynamic: license-file
